flatbread/__init__.py
flatbread/chaining.py
flatbread/config.py
flatbread/percentages.py
flatbread/tooling.py
flatbread/accessors/dataframe.py
flatbread/accessors/index.py
flatbread/accessors/series.py
flatbread/agg/aggregation.py
flatbread/agg/totals.py
flatbread/config/config.defaults.json
flatbread/render/config.py
flatbread/render/constants.py
flatbread/render/display.py
flatbread/render/tablespec.py
flatbread/render/template.jinja.html
flatbread/render/template.py
flatbread/testing/dataframe.py
flatbread-0.1.5.dist-info/METADATA
flatbread-0.1.5.dist-info/WHEEL
flatbread-0.1.5.dist-info/licenses/license.md
flatbread-0.1.5.dist-info/RECORD
