Metadata-Version: 2.4
Name: flatbread
Version: 0.1.5
Summary: Pandas extension for aggregation and tabular display
Project-URL: Homepage, https://github.com/lcvriend/flatbread
Author-email: "L.C. Vriend" <vanboefer@gmail.com>
License: # GNU GENERAL PUBLIC LICENSE
License-File: license.md
Keywords: aggregation,dataframe,display,extension,pandas,tables
Classifier: Development Status :: 4 - Beta
Classifier: Intended Audience :: Developers
Classifier: License :: OSI Approved :: GNU General Public License v3 (GPLv3)
Classifier: Operating System :: OS Independent
Classifier: Programming Language :: Python :: 3
Classifier: Programming Language :: Python :: 3.10
Classifier: Programming Language :: Python :: 3.11
Classifier: Programming Language :: Python :: 3.12
Classifier: Topic :: Software Development :: Libraries :: Python Modules
Requires-Python: >=3.10
Requires-Dist: jinja2
Requires-Dist: pandas>=2.0.0
